setup.py
browsermob_proxy.egg-info/PKG-INFO
browsermob_proxy.egg-info/SOURCES.txt
browsermob_proxy.egg-info/dependency_links.txt
browsermob_proxy.egg-info/requires.txt
browsermob_proxy.egg-info/top_level.txt
browsermobproxy/__init__.py
browsermobproxy/client.py
browsermobproxy/server.py
browsermobproxy/webdriver_event_listener.py
test/test_client.py
test/test_remote.py
test/test_webdriver.py